{"code": 0, "message": "OK", "data": {"search_token": "1586585695845274", "server_url": "https://europe-company.taxify.eu", "country": "ua", "city": "Lviv", "search_categories": [{"id": 859, "name": "Isolated", "seats": 3, "description": "Car with a screen between driver and passenger", "disclaimer": "", "car_icon_url": "https://images.bolt.eu/store/2020/2020-03-30/5133c5b2-7d1f-4d1c-bfd4-1dc281de4961.png", "category_icon_url": "https://images.bolt.eu/store/2020/2020-03-30/b2b32c7f-9898-4e30-9ad5-176a93579ac9.png", "route_id": "0", "eta_info": {"pickup_eta": 120}, "price": {"lock_hash": "MvS9kr7Yb2wuXwLg", "surge_multiplier": 1, "actual": "73\u20b4"}, "action": {"type": "order", "can_create_order": true, "show_surge_confirmation": false}, "info": [{"name": "Fare", "value": "73\u20b4", "children": [{"name": "Minimum price", "value": "35.00\u20b4"}, {"name": "Start", "value": "21.00\u20b4"}, {"name": "Per km", "value": "5.00\u20b4/KM"}, {"name": "Per min", "value": "1.20\u20b4/MIN"}]}, {"name": "Wait time", "value": "1.20\u20b4/MIN"}, {"name": "Cancellation", "value": "35.00\u20b4"}, {"name": "Seats", "value": "3"}], "drivers": [{"id": 2205268123, "lat": 49.8160113, "lng": 24.0290937, "bearing": 295.75507}, {"id": 3754501874, "lat": 49.8253475, "lng": 24.0209609, "bearing": 90}, {"id": 1025136985, "lat": 49.8213242647, "lng": 24.0166858491, "bearing": 223.2421875}, {"id": 3813443389, "lat": 49.8228401, "lng": 24.0126333, "bearing": 0}, {"id": 3562970880, "lat": 49.8264933, "lng": 24.0177933, "bearing": 131}, {"id": 1707829704, "lat": 49.8229976, "lng": 24.0090825, "bearing": 94.660614}, {"id": 1781382215, "lat": 49.8229377, "lng": 24.0088388, "bearing": 336.74567}, {"id": 1647716855, "lat": 49.825467, "lng": 24.0127633, "bearing": 153.64658}, {"id": 123139925, "lat": 49.8165955, "lng": 24.0416683, "bearing": 181.7593}, {"id": 4062688965, "lat": 49.8171980633, "lng": 24.0022895951, "bearing": -1}, {"id": 3875355606, "lat": 49.826608, "lng": 24.0430718, "bearing": 119.03208}, {"id": 2657124810, "lat": 49.8338118, "lng": 24.0192077, "bearing": 180}]}, {"id": 362, "name": "Bolt", "seats": 4, "description": "", "disclaimer": "", "car_icon_url": "https://images.bolt.eu/store/2019/2019-10-16/fcdc1b52-30a7-4081-adbf-db58d349e184.png", "category_icon_url": "https://images.bolt.eu/store/2019/403f6c2643ea6cab08c35da4a32865b6/653/246", "route_id": "0", "eta_info": {"pickup_eta": 120}, "price": {"lock_hash": "MvS9kr7Yb2wuXwLg", "surge_multiplier": 1, "actual": "73\u20b4"}, "action": {"type": "order", "can_create_order": true, "show_surge_confirmation": false}, "info": [{"name": "Fare", "value": "73\u20b4", "children": [{"name": "Minimum price", "value": "35.00\u20b4"}, {"name": "Start", "value": "21.00\u20b4"}, {"name": "Per km", "value": "5.00\u20b4/KM"}, {"name": "Per min", "value": "1.20\u20b4/MIN"}]}, {"name": "Wait time", "value": "1.20\u20b4/MIN"}, {"name": "Cancellation", "value": "35.00\u20b4"}, {"name": "Seats", "value": "4"}], "drivers": [{"id": 2205268123, "lat": 49.8160113, "lng": 24.0290937, "bearing": 295.75507}, {"id": 3641353346, "lat": 49.819572, "lng": 24.0194799, "bearing": 92.96476}, {"id": 1944704516, "lat": 49.8184985156, "lng": 24.0207053069, "bearing": -1}, {"id": 1799613894, "lat": 49.825206, "lng": 24.0211847, "bearing": 180}, {"id": 1025136985, "lat": 49.8213242647, "lng": 24.0166858491, "bearing": 223.2421875}, {"id": 226656957, "lat": 49.8113533, "lng": 24.0257283, "bearing": 180.08604}, {"id": 3754501874, "lat": 49.8253475, "lng": 24.0209609, "bearing": 90}, {"id": 3813443389, "lat": 49.8228401, "lng": 24.0126333, "bearing": 0}, {"id": 3562970880, "lat": 49.8264933, "lng": 24.0177933, "bearing": 131}, {"id": 1622802715, "lat": 49.8081795948, "lng": 24.0186994561, "bearing": 94.1937255859}, {"id": 1707829704, "lat": 49.8229976, "lng": 24.0090825, "bearing": 94.660614}, {"id": 1647716855, "lat": 49.825467, "lng": 24.0127633, "bearing": 153.64658}]}, {"id": 728, "name": "Delivery", "seats": 1, "description": "Fast delivery", "disclaimer": "", "car_icon_url": "https://images.bolt.eu/store/2020/2020-02-03/29f7841e-16d1-4332-8e35-a9c8e248fded.png", "category_icon_url": "https://images.bolt.eu/store/2020/2020-02-03/e1a76e76-e055-4b39-aa3a-e645a5d9bf0b.png", "route_id": "0", "eta_info": {"pickup_eta": 120}, "price": {"lock_hash": "MvS9kr7Yb2wuXwLg", "surge_multiplier": 1, "actual": "93\u20b4"}, "action": {"type": "order", "can_create_order": true, "show_surge_confirmation": false}, "info": [{"name": "Fare", "value": "93\u20b4", "children": [{"name": "Minimum price", "value": "41.00\u20b4"}, {"name": "Start", "value": "41.00\u20b4"}, {"name": "Per km", "value": "5.00\u20b4/KM"}, {"name": "Per min", "value": "1.20\u20b4/MIN"}]}, {"name": "Wait time", "value": "1.20\u20b4/MIN"}, {"name": "Cancellation", "value": "41.00\u20b4"}, {"name": "Seats", "value": "1"}], "drivers": [{"id": 2205268123, "lat": 49.8160113, "lng": 24.0290937, "bearing": 295.75507}, {"id": 3641353346, "lat": 49.819572, "lng": 24.0194799, "bearing": 92.96476}, {"id": 1944704516, "lat": 49.8184985156, "lng": 24.0207053069, "bearing": -1}, {"id": 1799613894, "lat": 49.825206, "lng": 24.0211847, "bearing": 180}, {"id": 1025136985, "lat": 49.8213242647, "lng": 24.0166858491, "bearing": 223.2421875}, {"id": 226656957, "lat": 49.8113533, "lng": 24.0257283, "bearing": 180.08604}, {"id": 3754501874, "lat": 49.8253475, "lng": 24.0209609, "bearing": 90}, {"id": 3813443389, "lat": 49.8228401, "lng": 24.0126333, "bearing": 0}, {"id": 3562970880, "lat": 49.8264933, "lng": 24.0177933, "bearing": 131}, {"id": 1622802715, "lat": 49.8081795948, "lng": 24.0186994561, "bearing": 94.1937255859}, {"id": 1707829704, "lat": 49.8229976, "lng": 24.0090825, "bearing": 94.660614}, {"id": 1647716855, "lat": 49.825467, "lng": 24.0127633, "bearing": 153.64658}]}, {"id": 369, "name": "Comfort", "seats": 4, "description": "", "disclaimer": "", "car_icon_url": "https://images.bolt.eu/store/2019/2019-10-16/d5745690-d7f4-4beb-bea9-3c131521160d.png", "category_icon_url": "https://images.bolt.eu/store/2019/2019-09-05/bb7d7782-dabb-4a3d-8d1f-01846ed06fd3", "route_id": "0", "eta_info": {"pickup_eta": 120}, "price": {"lock_hash": "MvS9kr7Yb2wuXwLg", "surge_multiplier": 1, "actual": "85\u20b4"}, "action": {"type": "order", "can_create_order": true, "show_surge_confirmation": false}, "info": [{"name": "Fare", "value": "85\u20b4", "children": [{"name": "Minimum price", "value": "50.00\u20b4"}, {"name": "Start", "value": "28.00\u20b4"}, {"name": "Per km", "value": "5.30\u20b4/KM"}, {"name": "Per min", "value": "1.35\u20b4/MIN"}]}, {"name": "Wait time", "value": "1.35\u20b4/MIN"}, {"name": "Cancellation", "value": "50.00\u20b4"}, {"name": "Seats", "value": "4"}], "drivers": [{"id": 2205268123, "lat": 49.8160113, "lng": 24.0290937, "bearing": 295.75507}, {"id": 3754501874, "lat": 49.8253475, "lng": 24.0209609, "bearing": 90}, {"id": 3641353346, "lat": 49.819572, "lng": 24.0194799, "bearing": 92.96476}, {"id": 1799613894, "lat": 49.825206, "lng": 24.0211847, "bearing": 180}, {"id": 1025136985, "lat": 49.8213242647, "lng": 24.0166858491, "bearing": 223.2421875}, {"id": 3813443389, "lat": 49.8228401, "lng": 24.0126333, "bearing": 0}, {"id": 3562970880, "lat": 49.8264933, "lng": 24.0177933, "bearing": 131}, {"id": 1647716855, "lat": 49.825467, "lng": 24.0127633, "bearing": 153.64658}, {"id": 1781382215, "lat": 49.8229377, "lng": 24.0088388, "bearing": 336.74567}, {"id": 1724999894, "lat": 49.8102287122, "lng": 24.0123069039, "bearing": 20.68983078}, {"id": 3305433147, "lat": 49.8083925, "lng": 24.01669, "bearing": 0}, {"id": 3184011117, "lat": 49.8129455, "lng": 24.0386632, "bearing": 223.70352}]}, {"id": 733, "name": "Pets", "seats": 4, "description": "Animal friendly", "disclaimer": "", "car_icon_url": "https://images.bolt.eu/store/2020/2020-02-03/f10d99e3-dd65-4e3f-a7d2-3a8b5eb11c9a.png", "category_icon_url": "https://images.bolt.eu/store/2020/2020-02-03/1c44cb24-0693-43e6-99f3-4fd5ce04e25b.png", "route_id": "0", "eta_info": {"pickup_eta": 120}, "price": {"lock_hash": "MvS9kr7Yb2wuXwLg", "surge_multiplier": 1, "actual": "93\u20b4"}, "action": {"type": "order", "can_create_order": true, "show_surge_confirmation": false}, "info": [{"name": "Fare", "value": "93\u20b4", "children": [{"name": "Minimum price", "value": "41.00\u20b4"}, {"name": "Start", "value": "41.00\u20b4"}, {"name": "Per km", "value": "5.00\u20b4/KM"}, {"name": "Per min", "value": "1.20\u20b4/MIN"}]}, {"name": "Wait time", "value": "1.20\u20b4/MIN"}, {"name": "Cancellation", "value": "41.00\u20b4"}, {"name": "Seats", "value": "4"}], "drivers": [{"id": 2205268123, "lat": 49.8160113, "lng": 24.0290937, "bearing": 295.75507}, {"id": 3641353346, "lat": 49.819572, "lng": 24.0194799, "bearing": 92.96476}, {"id": 1944704516, "lat": 49.8184985156, "lng": 24.0207053069, "bearing": -1}, {"id": 1799613894, "lat": 49.825206, "lng": 24.0211847, "bearing": 180}, {"id": 1025136985, "lat": 49.8213242647, "lng": 24.0166858491, "bearing": 223.2421875}, {"id": 226656957, "lat": 49.8113533, "lng": 24.0257283, "bearing": 180.08604}, {"id": 3754501874, "lat": 49.8253475, "lng": 24.0209609, "bearing": 90}, {"id": 3813443389, "lat": 49.8228401, "lng": 24.0126333, "bearing": 0}, {"id": 3562970880, "lat": 49.8264933, "lng": 24.0177933, "bearing": 131}, {"id": 1622802715, "lat": 49.8081795948, "lng": 24.0186994561, "bearing": 94.1937255859}, {"id": 1707829704, "lat": 49.8229976, "lng": 24.0090825, "bearing": 94.660614}, {"id": 1647716855, "lat": 49.825467, "lng": 24.0127633, "bearing": 153.64658}]}], "routes": [{"id": "0", "elements": [{"type": "walking", "points": "qaaoHk}rqCPEPEFA"}, {"type": "driving", "points": "e`aoHw}rqCVdBa@tAgAKeAxIwe@uBs@e@q@fAoGlOwEgEo@SwC~B_A\\uRg@O\\mEuAoAw@qB}C_A{@yAiDsE{HuPc\\wBwIAcA[g@yBjB_W|MmB]A]mAJu@dAs@vDWZgLiAoD@}IbFyc@`PcBWa@~@w@x@wu@d\\oB^}CEc@XOb@tDrG"}]}]}}